etc/default/networking
etc/network/ifupdown2/addons.conf
etc/network/ifupdown2/ifupdown2.conf
ifupdown2/__init__.py
ifupdown2/__main__.py
ifupdown2/addons/__init__.py
ifupdown2/addons/address.py
ifupdown2/addons/addressvirtual.py
ifupdown2/addons/bond.py
ifupdown2/addons/bridge.py
ifupdown2/addons/bridgevlan.py
ifupdown2/addons/dhcp.py
ifupdown2/addons/ethtool.py
ifupdown2/addons/link.py
ifupdown2/addons/mstpctl.py
ifupdown2/addons/ppp.py
ifupdown2/addons/tunnel.py
ifupdown2/addons/usercmds.py
ifupdown2/addons/vlan.py
ifupdown2/addons/vrf.py
ifupdown2/addons/vrrpd.py
ifupdown2/addons/vxlan.py
ifupdown2/ifupdown/__init__.py
ifupdown2/ifupdown/argv.py
ifupdown2/ifupdown/config.py
ifupdown2/ifupdown/exceptions.py
ifupdown2/ifupdown/graph.py
ifupdown2/ifupdown/iface.py
ifupdown2/ifupdown/iff.py
ifupdown2/ifupdown/ifupdownbase.py
ifupdown2/ifupdown/ifupdownconfig.py
ifupdown2/ifupdown/ifupdownflags.py
ifupdown2/ifupdown/ifupdownmain.py
ifupdown2/ifupdown/log.py
ifupdown2/ifupdown/main.py
ifupdown2/ifupdown/netlink.py
ifupdown2/ifupdown/networkinterfaces.py
ifupdown2/ifupdown/policymanager.py
ifupdown2/ifupdown/scheduler.py
ifupdown2/ifupdown/statemanager.py
ifupdown2/ifupdown/template.py
ifupdown2/ifupdown/utils.py
ifupdown2/ifupdownaddons/LinkUtils.py
ifupdown2/ifupdownaddons/__init__.py
ifupdown2/ifupdownaddons/cache.py
ifupdown2/ifupdownaddons/dhclient.py
ifupdown2/ifupdownaddons/modulebase.py
ifupdown2/ifupdownaddons/mstpctlutil.py
ifupdown2/ifupdownaddons/systemutils.py
ifupdown2/ifupdownaddons/utilsbase.py
ifupdown2/nlmanager/__init__.py
ifupdown2/nlmanager/nllistener.py
ifupdown2/nlmanager/nlmanager.py
ifupdown2/nlmanager/nlpacket.py
ifupdown2-1.2.1.dist-info/METADATA
ifupdown2-1.2.1.dist-info/RECORD
ifupdown2-1.2.1.dist-info/WHEEL
ifupdown2-1.2.1.dist-info/entry_points.txt
ifupdown2-1.2.1.dist-info/top_level.txt
